gc7_007/__init__.py
gc7_007/commits_semantic.md
gc7_007/compare_keys.py
gc7_007/convert_readme.py
gc7_007/hello.py
gc7_007-1.0.0.dist-info/METADATA
gc7_007-1.0.0.dist-info/WHEEL
gc7_007-1.0.0.dist-info/top_level.txt
gc7_007-1.0.0.dist-info/RECORD
