Metadata-Version: 2.4
Name: gc7_007
Version: 1.0.0
Summary: Un module avec plein d'outils utiles pour devs en PyMoX (PY-thon - MO-jo - Flet-X)
Author-email: GrCOTE7 <GrCOTE7@gmail.com>
License-Expression: MIT
Classifier: Programming Language :: Python :: 3
Classifier: Operating System :: OS Independent
Requires-Python: >=3.10
